py_judged/__init__.py
py_judged/judger_utils.py
py_judged/resources.py
py_judged/runner.py
py_judged/sympy_utils.py
py_judged/utils.py
py_judged-0.0.1.dist-info/LICENSE
py_judged-0.0.1.dist-info/METADATA
py_judged-0.0.1.dist-info/WHEEL
py_judged-0.0.1.dist-info/top_level.txt
py_judged-0.0.1.dist-info/RECORD
